serialdaq/__init__.py
serialdaq/serialdaq.py
serialdaq-0.1.3.dist-info/LICENSE
serialdaq-0.1.3.dist-info/WHEEL
serialdaq-0.1.3.dist-info/METADATA
serialdaq-0.1.3.dist-info/RECORD
